iscan/__init__.py
iscan/scan.py
iscan/std_lib.py
iscan/tests/__init__.py
iscan/tests/test_scan.py
iscan/tests/test_std_lib.py
iscan/tests/test_modules/__init__.py
iscan/tests/test_modules/absolute.py
iscan/tests/test_modules/mixed.py
iscan/tests/test_modules/relative.py
iscan/tests/test_package/__init__.py
iscan/tests/test_package/foo.py
iscan/tests/test_package/city/__init__.py
iscan/tests/test_package/city/boo.py
iscan/tests/test_package/city/borough/__init__.py
iscan/tests/test_package/city/borough/tricky.py
iscan/tests/test_package/country/__init__.py
iscan/tests/test_package/country/baz.py
iscan/tests/test_package/country/state/__init__.py
iscan/tests/test_package/country/state/wow.py
iscan-0.4.5.dist-info/licenses/LICENSE
iscan-0.4.5.dist-info/METADATA
iscan-0.4.5.dist-info/WHEEL
iscan-0.4.5.dist-info/entry_points.txt
iscan-0.4.5.dist-info/top_level.txt
iscan-0.4.5.dist-info/RECORD
