Metadata-Version: 2.4
Name: iscan
Version: 0.4.5
Summary: iscan helps you identify your project's dependencies.
Home-page: https://github.com/zzhengnan/iscan
Author: Zhengnan Zhao
Classifier: Programming Language :: Python :: 3.9
Classifier: Programming Language :: Python :: 3.10
Classifier: Programming Language :: Python :: 3.11
Classifier: Programming Language :: Python :: 3.12
Classifier: Programming Language :: Python :: 3.13
Classifier: License :: OSI Approved :: MIT License
Classifier: Operating System :: OS Independent
Requires-Python: >=3.9
License-File: LICENSE
Provides-Extra: build
Requires-Dist: setuptools; extra == "build"
Requires-Dist: twine; extra == "build"
Requires-Dist: wheel; extra == "build"
Provides-Extra: qa
Requires-Dist: flake8; extra == "qa"
Requires-Dist: isort; extra == "qa"
Requires-Dist: pre-commit; extra == "qa"
Provides-Extra: test
Requires-Dist: coverage; extra == "test"
Requires-Dist: mypy; extra == "test"
Requires-Dist: pytest; extra == "test"
Provides-Extra: util
Requires-Dist: beautifulsoup4; extra == "util"
Requires-Dist: requests; extra == "util"
Provides-Extra: dev
Requires-Dist: setuptools; extra == "dev"
Requires-Dist: twine; extra == "dev"
Requires-Dist: wheel; extra == "dev"
Requires-Dist: flake8; extra == "dev"
Requires-Dist: isort; extra == "dev"
Requires-Dist: pre-commit; extra == "dev"
Requires-Dist: coverage; extra == "dev"
Requires-Dist: mypy; extra == "dev"
Requires-Dist: pytest; extra == "dev"
Requires-Dist: beautifulsoup4; extra == "dev"
Requires-Dist: requests; extra == "dev"
Dynamic: author
Dynamic: classifier
Dynamic: description
Dynamic: description-content-type
Dynamic: home-page
Dynamic: license-file
Dynamic: provides-extra
Dynamic: requires-python
Dynamic: summary
